LICENSE
MANIFEST.in
README.rst
setup.py
pickle5/__init__.py
pickle5/_pickle.c
pickle5/compat.h
pickle5/pickle.py
pickle5/picklebufobject.c
pickle5/picklebufobject.h
pickle5/pickletools.py
pickle5.egg-info/PKG-INFO
pickle5.egg-info/SOURCES.txt
pickle5.egg-info/dependency_links.txt
pickle5.egg-info/top_level.txt
pickle5/clinic/_pickle-3.6.c.h
pickle5/clinic/_pickle-3.7.c.h
pickle5/clinic/_pickle.c.h
pickle5/test/__init__.py
pickle5/test/pickletester.py
pickle5/test/test_pickle.py
pickle5/test/test_picklebuffer.py