Metadata-Version: 2.1
Name: pickle5
Version: 0.0.9
Summary: Backport of the pickle 5 protocol (PEP 574) and other pickle changes
Home-page: https://github.com/pitrou/pickle5-backport
Author: Antoine Pitrou
Author-email: antoine@python.org
License: UNKNOWN
Platform: UNKNOWN
Classifier: Development Status :: 4 - Beta
Classifier: Intended Audience :: Developers
Classifier: License :: OSI Approved :: Python Software Foundation License
Classifier: Operating System :: OS Independent
Classifier: Programming Language :: Python :: 3
Classifier: Programming Language :: Python :: 3.6
Classifier: Programming Language :: Python :: 3.7
Classifier: Programming Language :: Python :: Implementation :: CPython
